fastpluggy_plugin/__init__.py
fastpluggy_plugin/bootstrap.py
fastpluggy_plugin/auth_user/__init__.py
fastpluggy_plugin/auth_user/config.py
fastpluggy_plugin/auth_user/models.py
fastpluggy_plugin/auth_user/plugin.py
fastpluggy_plugin/auth_user/repository.py
fastpluggy_plugin/auth_user/auth/__init__.py
fastpluggy_plugin/auth_user/auth/basic_auth.py
fastpluggy_plugin/auth_user/auth/session_auth.py
fastpluggy_plugin/auth_user/routers/__init__.py
fastpluggy_plugin/auth_user/routers/admin.py
fastpluggy_plugin/auth_user/routers/login.py
fastpluggy_plugin/auth_user/routers/profile.py
fastpluggy_plugin/auth_user/templates/profile.html.j2
fastpluggy_plugin/crud_tools/__init__.py
fastpluggy_plugin/crud_tools/config.py
fastpluggy_plugin/crud_tools/crud_admin.py
fastpluggy_plugin/crud_tools/crud_admin_registry.py
fastpluggy_plugin/crud_tools/crud_link_helper.py
fastpluggy_plugin/crud_tools/menu_tools.py
fastpluggy_plugin/crud_tools/plugin.py
fastpluggy_plugin/crud_tools/schema.py
fastpluggy_plugin/crud_tools/template_tools.py
fastpluggy_plugin/crud_tools/field_types/__init__.py
fastpluggy_plugin/crud_tools/field_types/date_fields.py
fastpluggy_plugin/crud_tools/field_types/dynamic_fields.py
fastpluggy_plugin/crud_tools/field_types/entity_fields.py
fastpluggy_plugin/crud_tools/field_types/enum_fields.py
fastpluggy_plugin/crud_tools/field_types/timedelta_fields.py
fastpluggy_plugin/crud_tools/filters/__init__.py
fastpluggy_plugin/crud_tools/filters/boolean_filter.py
fastpluggy_plugin/crud_tools/filters/filter_factory.py
fastpluggy_plugin/crud_tools/filters/filtered_table.py
fastpluggy_plugin/crud_tools/filters/number_filter.py
fastpluggy_plugin/crud_tools/filters/text_filter.py
fastpluggy_plugin/crud_tools/router/__init__.py
fastpluggy_plugin/crud_tools/router/api.py
fastpluggy_plugin/crud_tools/router/crud.py
fastpluggy_plugin/crud_tools/router/crud_admin.py
fastpluggy_plugin/crud_tools/static/css/header_filters.css
fastpluggy_plugin/crud_tools/static/js/dynamic-select.js
fastpluggy_plugins-0.0.50.dist-info/METADATA
fastpluggy_plugins-0.0.50.dist-info/WHEEL
fastpluggy_plugins-0.0.50.dist-info/entry_points.txt
fastpluggy_plugins-0.0.50.dist-info/top_level.txt
fastpluggy_plugins-0.0.50.dist-info/RECORD
