Metadata-Version: 2.4
Name: fastpluggy-plugins
Version: 0.0.50
Summary: Official plugin bundle for FastPluggy
Author-email: Your Name <you@example.com>
Requires-Python: >=3.10
Requires-Dist: jinja2
Requires-Dist: redis
Requires-Dist: croniter
Requires-Dist: psutil
Requires-Dist: loguru
Requires-Dist: prometheus_client
Requires-Dist: babel
Requires-Dist: passlib
Requires-Dist: python-jose
Requires-Dist: python-multipart
Requires-Dist: packaging
Provides-Extra: crud-tools
Requires-Dist: jinja2; extra == "crud-tools"
Provides-Extra: redis-tools
Requires-Dist: redis; extra == "redis-tools"
Provides-Extra: tasks-worker
Requires-Dist: croniter; extra == "tasks-worker"
Requires-Dist: psutil; extra == "tasks-worker"
Provides-Extra: scheduled-query
Requires-Dist: loguru; extra == "scheduled-query"
Requires-Dist: prometheus_client; extra == "scheduled-query"
Provides-Extra: ui-tools
Requires-Dist: babel; extra == "ui-tools"
Requires-Dist: jinja2; extra == "ui-tools"
Provides-Extra: debug-tools
Requires-Dist: packaging; extra == "debug-tools"
Provides-Extra: auth-user
Requires-Dist: passlib; extra == "auth-user"
Requires-Dist: python-jose; extra == "auth-user"
Requires-Dist: python-multipart; extra == "auth-user"
Provides-Extra: all
Requires-Dist: babel; extra == "all"
Requires-Dist: croniter; extra == "all"
Requires-Dist: jinja2; extra == "all"
Requires-Dist: loguru; extra == "all"
Requires-Dist: passlib; extra == "all"
Requires-Dist: prometheus_client; extra == "all"
Requires-Dist: psutil; extra == "all"
Requires-Dist: python-jose; extra == "all"
Requires-Dist: python-multipart; extra == "all"
Requires-Dist: redis; extra == "all"
Requires-Dist: packaging; extra == "all"
